drivedl/__init__.py
drivedl/drivedl.py
drivedl/util.py
drivedl-1.2.dist-info/LICENSE
drivedl-1.2.dist-info/METADATA
drivedl-1.2.dist-info/WHEEL
drivedl-1.2.dist-info/entry_points.txt
drivedl-1.2.dist-info/top_level.txt
drivedl-1.2.dist-info/RECORD
