Metadata-Version: 2.1
Name: drivedl
Version: 1.2
Summary: Download files from Google Drive (inclusive of teamdrives, shared with me and my drive) concurrently.
Home-page: https://github.com/architdate/drivedl
Author: Archit Date
Author-email: architdate@gmail.com
License: MIT
Platform: UNKNOWN
Classifier: License :: OSI Approved :: MIT License
Classifier: Programming Language :: Python
Classifier: Programming Language :: Python :: 3.6
Classifier: Programming Language :: Python :: 3.7
Classifier: Programming Language :: Python :: 3.8
Requires-Python: >=3.6
Requires-Dist: google-api-python-client
Requires-Dist: google-auth-httplib2
Requires-Dist: google-auth-oauthlib
Requires-Dist: tqdm
Requires-Dist: colorama
